project/__init__.py
project/main.py
project/other_module.py
test_layers-0.1.0.dist-info/METADATA
test_layers-0.1.0.dist-info/WHEEL
test_layers-0.1.0.dist-info/top_level.txt
test_layers-0.1.0.dist-info/RECORD
