Metadata-Version: 2.4
Name: test-layers
Version: 0.1.0
Summary: Test linters
Requires-Python: >=3.13
Requires-Dist: bounded-contexts-linter>=1.0.0
Requires-Dist: di-linter>=1.1.0
Requires-Dist: domain-types-linter>=1.0.0
Requires-Dist: layers-linter>=3.1.0
Requires-Dist: python-telegram-bot>=22.1
